{
  "Owner": "AWS",
  "RuleSetName": "NIST800-53Rev4",
  "BuildVersion": "0.1.0",
  "Description" : "AWS Guard rule set based on the AWS Config Conformance Pack for NIST 800-53 revision 4.",
  "Contact" : "aws-guard-rules-registry@amazon.com",
  "Rules": [
    {
      "AWSConfigIdentifier": "SECRETSMANAGER_SCHEDULED_ROTATION_SUCCESS_CHECK",
      "CfnGuardFile": "rules/aws/secrets_manager/secretsmanager_scheduled_rotation_success_check.guard",
      "Controls": [
        "AC-2(1)",
        "AC-2(j)"
      ]
    },
    {
      "AWSConfigIdentifier": "IAM_USER_GROUP_MEMBERSHIP_CHECK",
      "CfnGuardFile": "rules/aws/iam/iam_user_group_membership_check.guard",
      "Controls": [
        "AC-2(1)",
        "AC-2(j)",
        "AC-3",
        "AC-6"
      ]
    },
    {
      "AWSConfigIdentifier": "IAM_PASSWORD_POLICY",
      "CfnGuardFile": "rules/aws/iam/iam_password_policy.guard",
      "Controls": [
        "AC-2(1)",
        "AC-2(f)",
        "AC-2(j)",
        "IA-2",
        "IA-5(1)(a)(d)(e)",
        "IA-5(4)"
      ]
    },
    {
      "AWSConfigIdentifier": "ACCESS_KEYS_ROTATED",
      "CfnGuardFile": "rules/aws/iam/access_keys_rotated.guard",
      "Controls": [
        "AC-2(1)",
        "AC-2(j)"
      ]
    },
    {
      "AWSConfigIdentifier": "IAM_USER_UNUSED_CREDENTIALS_CHECK",
      "CfnGuardFile": "rules/aws/iam/iam_user_unused_credentials_check.guard",
      "Controls": [
        "AC-2(1)",
        "AC-2(3)",
        "AC-2(f)",
        "AC-3",
        "AC-6"
      ]
    },
    {
      "AWSConfigIdentifier": "SECURITYHUB_ENABLED",
      "CfnGuardFile": "rules/aws/security_hub/securityhub_enabled.guard",
      "Controls": [
        "AC-2(1)",
        "AC-2(4)",
        "AC-2(12)(a)",
        "AC-2(g)",
        "AC-17(1)",
        "AU-6(1)(3)",
        "CA-7(a)(b)",
        "SA-10",
        "SI-4(2)",
        "SI-4(4)",
        "SI-4(5)",
        "SI-4(16)",
        "SI-4(a)(b)(c)"
      ]
    },
    {
      "AWSConfigIdentifier": "GUARDDUTY_ENABLED_CENTRALIZED",
      "CfnGuardFile": "rules/aws/guardduty/guardduty_enabled_centralized.guard",
      "Controls": [
        "AC-2(1)",
        "AC-2(4)",
        "AC-2(12)(a)",
        "AC-2(g)",
        "AC-17(1)",
        "AU-6(1)(3)",
        "CA-7(a)(b)",
        "RA-5",
        "SA-10",
        "SI-4(1)",
        "SI-4(2)",
        "SI-4(4)",
        "SI-4(5)",
        "SI-4(16)",
        "SI-4(a)(b)(c)"
      ]
    },
    {
      "AWSConfigIdentifier": "CLOUD_TRAIL_CLOUD_WATCH_LOGS_ENABLED",
      "CfnGuardFile": "rules/aws/cloudtrail/cloud_trail_cloud_watch_logs_enabled.guard",
      "Controls": [
        "AC-2(4)",
        "AC-2(g)",
        "AU-2(a)(d)",
        "AU-3",
        "AU-6(1)(3)",
        "AU-7(1)",
        "AU-12(a)(c)",
        "CA-7(a)(b)",
        "SI-4(2)",
        "SI-4(4)",
        "SI-4(5)",
        "SI-4(a)(b)(c)"
      ]
    },
    {
      "AWSConfigIdentifier": "CLOUDTRAIL_ENABLED",
      "CfnGuardFile": "rules/aws/cloudtrail/cloudtrail_enabled.guard",
      "Controls": [
        "AC-2(4)",
        "AC-2(g)",
        "AU-2(a)(d)",
        "AU-3",
        "AU-12(a)(c)"
      ]
    },
    {
      "AWSConfigIdentifier": "MULTI_REGION_CLOUDTRAIL_ENABLED",
      "CfnGuardFile": "rules/aws/cloudtrail/multi_region_cloudtrail_enabled.guard",
      "Controls": [
        "AC-2(4)",
        "AU-2(a)(d)",
        "AU-3",
        "AU-12(a)(c)"
      ]
    },
    {
      "AWSConfigIdentifier": "RDS_LOGGING_ENABLED",
      "CfnGuardFile": "rules/aws/amazon_rds/rds_logging_enabled.guard",
      "Controls": [
        "AC-2(4)",
        "AC-2(g)",
        "AU-2(a)(d)",
        "AU-3",
        "AU-12(a)(c)"
      ]
    },
    {
      "AWSConfigIdentifier": "CLOUDWATCH_ALARM_ACTION_CHECK",
      "CfnGuardFile": "rules/aws/cloudwatch/cloudwatch_alarm_action_check.guard",
      "Controls": [
        "AC-2(4)",
        "AU-6(1)(3)",
        "AU-7(1)",
        "CA-7(a)(b)",
        "IR-4(1)",
        "SI-4(2)",
        "SI-4(4)",
        "SI-4(5)",
        "SI-4(a)(b)(c)"
      ]
    },
    {
      "AWSConfigIdentifier": "REDSHIFT_CLUSTER_CONFIGURATION_CHECK",
      "CfnGuardFile": "rules/aws/amazon_redshift/redshift_cluster_configuration_check.guard",
      "Controls": [
        "AC-2(4)",
        "AC-2(g)",
        "AU-2(a)(d)",
        "AU-3",
        "AU-12(a)(c)",
        "SC-13",
        "SC-28"
      ]
    },
    {
      "AWSConfigIdentifier": "IAM_ROOT_ACCESS_KEY_CHECK",
      "CfnGuardFile": "rules/aws/iam/iam_root_access_key_check.guard",
      "Controls": [
        "AC-2(f)",
        "AC-2(j)",
        "AC-3",
        "AC-6",
        "AC-6(10)"
      ]
    },
    {
      "AWSConfigIdentifier": "S3_BUCKET_LOGGING_ENABLED",
      "CfnGuardFile": "rules/aws/amazon_s3/s3_bucket_logging_enabled.guard",
      "Controls": [
        "AC-2(g)",
        "AU-2(a)(d)",
        "AU-3",
        "AU-12(a)(c)"
      ]
    },
    {
      "AWSConfigIdentifier": "CLOUDTRAIL_S3_DATAEVENTS_ENABLED",
      "CfnGuardFile": "rules/aws/cloudtrail/cloudtrail_s3_dataevents_enabled.guard",
      "Controls": [
        "AC-2(g)",
        "AU-2(a)(d)",
        "AU-3",
        "AU-12(a)(c)"
      ]
    },
    {
      "AWSConfigIdentifier": "ROOT_ACCOUNT_MFA_ENABLED",
      "CfnGuardFile": "rules/aws/iam/root_account_mfa_enabled.guard",
      "Controls": [
        "AC-2(j)",
        "IA-2(1)(11)"
      ]
    },
    {
      "AWSConfigIdentifier": "EMR_KERBEROS_ENABLED",
      "CfnGuardFile": "rules/aws/amazon_emr/emr_kerberos_enabled.guard",
      "Controls": [
        "AC-2(j)",
        "AC-3",
        "AC-5c",
        "AC-6"
      ]
    },
    {
      "AWSConfigIdentifier": "IAM_GROUP_HAS_USERS_CHECK",
      "CfnGuardFile": "rules/aws/iam/iam_group_has_users_check.guard",
      "Controls": [
        "AC-2(j)",
        "AC-3",
        "AC-5c",
        "AC-6",
        "SC-2"
      ]
    },
    {
      "AWSConfigIdentifier": "IAM_POLICY_NO_STATEMENTS_WITH_ADMIN_ACCESS",
      "CfnGuardFile": "rules/aws/iam/iam_policy_no_statements_with_admin_access.guard",
      "Controls": [
        "AC-2(j)",
        "AC-3",
        "AC-5c",
        "AC-6",
        "SC-2"
      ]
    },
    {
      "AWSConfigIdentifier": "IAM_USER_NO_POLICIES_CHECK",
      "CfnGuardFile": "rules/aws/iam/iam_user_no_policies_check.guard",
      "Controls": [
        "AC-2(j)",
        "AC-3",
        "AC-5c",
        "AC-6"
      ]
    },
    {
      "AWSConfigIdentifier": "S3_BUCKET_PUBLIC_WRITE_PROHIBITED",
      "CfnGuardFile": "rules/aws/amazon_s3/s3_bucket_public_write_prohibited.guard",
      "Controls": [
        "AC-3",
        "AC-4",
        "AC-6",
        "AC-21(b)",
        "SC-7",
        "SC-7(3)"
      ]
    },
    {
      "AWSConfigIdentifier": "LAMBDA_FUNCTION_PUBLIC_ACCESS_PROHIBITED",
      "CfnGuardFile": "rules/aws/lambda/lambda_function_public_access_prohibited.guard",
      "Controls": [
        "AC-3",
        "AC-4",
        "AC-6",
        "AC-21(b)",
        "SC-7",
        "SC-7(3)"
      ]
    },
    {
      "AWSConfigIdentifier": "RDS_SNAPSHOTS_PUBLIC_PROHIBITED",
      "CfnGuardFile": "rules/aws/amazon_rds/rds_snapshots_public_prohibited.guard",
      "Controls": [
        "AC-3",
        "AC-4",
        "AC-6",
        "AC-21(b)",
        "SC-7",
        "SC-7(3)"
      ]
    },
    {
      "AWSConfigIdentifier": "REDSHIFT_CLUSTER_PUBLIC_ACCESS_CHECK",
      "CfnGuardFile": "rules/aws/amazon_redshift/redshift_cluster_public_access_check.guard",
      "Controls": [
        "AC-3",
        "AC-4",
        "AC-6",
        "AC-21(b)",
        "SC-7",
        "SC-7(3)"
      ]
    },
    {
      "AWSConfigIdentifier": "S3_BUCKET_POLICY_GRANTEE_CHECK",
      "CfnGuardFile": "rules/aws/amazon_s3/s3_bucket_policy_grantee_check.guard",
      "Controls": [
        "AC-3",
        "AC-6",
        "SC-7",
        "SC-7(3)"
      ]
    },
    {
      "AWSConfigIdentifier": "S3_BUCKET_PUBLIC_READ_PROHIBITED",
      "CfnGuardFile": "rules/aws/amazon_s3/s3_bucket_public_read_prohibited.guard",
      "Controls": [
        "AC-3",
        "AC-4",
        "AC-6",
        "AC-21(b)",
        "SC-7",
        "SC-7(3)"
      ]
    },
    {
      "AWSConfigIdentifier": "S3_ACCOUNT_LEVEL_PUBLIC_ACCESS_BLOCKS",
      "CfnGuardFile": "rules/aws/amazon_s3/s3_account_level_public_access_blocks.guard",
      "Controls": [
        "AC-3",
        "AC-4",
        "AC-6",
        "AC-21(b)",
        "SC-7",
        "SC-7(3)"
      ]
    },
    {
      "AWSConfigIdentifier": "DMS_REPLICATION_NOT_PUBLIC",
      "CfnGuardFile": "rules/aws/aws_dms/dms_replication_not_public.guard",
      "Controls": [
        "AC-3",
        "AC-4",
        "AC-6",
        "AC-21(b)",
        "SC-7",
        "SC-7(3)"
      ]
    },
    {
      "AWSConfigIdentifier": "EBS_SNAPSHOT_PUBLIC_RESTORABLE_CHECK",
      "CfnGuardFile": "rules/aws/amazon_ec2/ebs_snapshot_public_restorable_check.guard",
      "Controls": [
        "AC-3",
        "AC-4",
        "AC-6",
        "AC-21(b)",
        "SC-7",
        "SC-7(3)"
      ]
    },
    {
      "AWSConfigIdentifier": "SAGEMAKER_NOTEBOOK_NO_DIRECT_INTERNET_ACCESS",
      "CfnGuardFile": "rules/aws/amazon_sagemaker/sagemaker_notebook_no_direct_internet_access.guard",
      "Controls": [
        "AC-3",
        "AC-4",
        "AC-6",
        "AC-21(b)",
        "SC-7",
        "SC-7(3)"
      ]
    },
    {
      "AWSConfigIdentifier": "RDS_INSTANCE_PUBLIC_ACCESS_CHECK",
      "CfnGuardFile": "rules/aws/amazon_rds/rds_instance_public_access_check.guard",
      "Controls": [
        "AC-4",
        "AC-6",
        "AC-21(b)",
        "SC-7",
        "SC-7(3)"
      ]
    },
    {
      "AWSConfigIdentifier": "LAMBDA_INSIDE_VPC",
      "CfnGuardFile": "rules/aws/lambda/lambda_inside_vpc.guard",
      "Controls": [
        "AC-4",
        "SC-7",
        "SC-7(3)"
      ]
    },
    {
      "AWSConfigIdentifier": "EC2_INSTANCES_IN_VPC",
      "CfnGuardFile": "rules/aws/amazon_ec2/ec2_instances_in_vpc.guard",
      "Controls": [
        "AC-4",
        "SC-7",
        "SC-7(3)"
      ]
    },
    {
      "AWSConfigIdentifier": "RESTRICTED_COMMON_PORTS",
      "CfnGuardFile": "rules/aws/amazon_ec2/restricted_common_ports.guard",
      "Controls": [
        "AC-4",
        "CM-2",
        "SC-7",
        "SC-7(3)"
      ]
    },
    {
      "AWSConfigIdentifier": "RESTRICTED_SSH",
      "CfnGuardFile": "rules/aws/amazon_ec2/restricted_ssh.guard",
      "Controls": [
        "AC-4",
        "SC-7",
        "SC-7(3)"
      ]
    },
    {
      "AWSConfigIdentifier": "VPC_DEFAULT_SECURITY_GROUP_CLOSED",
      "CfnGuardFile": "rules/aws/amazon_ec2/vpc_default_security_group_closed.guard",
      "Controls": [
        "AC-4",
        "SC-7",
        "SC-7(3)"
      ]
    },
    {
      "AWSConfigIdentifier": "VPC_SG_OPEN_ONLY_TO_AUTHORIZED_PORTS",
      "CfnGuardFile": "rules/aws/amazon_ec2/vpc_sg_open_only_to_authorized_ports.guard",
      "Controls": [
        "AC-4",
        "SC-7",
        "SC-7(3)"
      ]
    },
    {
      "AWSConfigIdentifier": "ACM_CERTIFICATE_EXPIRATION_CHECK",
      "CfnGuardFile": "rules/aws/aws_certificate_manager/acm_certificate_expiration_check.guard",
      "Controls": [
        "AC-4",
        "AC-17(2)",
        "SC-12"
      ]
    },
    {
      "AWSConfigIdentifier": "EC2_INSTANCE_NO_PUBLIC_IP",
      "CfnGuardFile": "rules/aws/amazon_ec2/ec2_instance_no_public_ip.guard",
      "Controls": [
        "AC-4",
        "AC-6",
        "AC-21(b)",
        "SC-7",
        "SC-7(3)"
      ]
    },
    {
      "AWSConfigIdentifier": "ELASTICSEARCH_IN_VPC_ONLY",
      "CfnGuardFile": "rules/aws/opensearch_service/elasticsearch_in_vpc_only.guard",
      "Controls": [
        "AC-4",
        "SC-7",
        "SC-7(3)"
      ]
    },
    {
      "AWSConfigIdentifier": "EMR_MASTER_NO_PUBLIC_IP",
      "CfnGuardFile": "rules/aws/amazon_emr/emr_master_no_public_ip.guard",
      "Controls": [
        "AC-4",
        "AC-21(b)",
        "SC-7",
        "SC-7(3)"
      ]
    },
    {
      "AWSConfigIdentifier": "INTERNET_GATEWAY_AUTHORIZED_VPC_ONLY",
      "CfnGuardFile": "rules/aws/amazon_ec2/internet_gateway_authorized_vpc_only.guard",
      "Controls": [
        "AC-4",
        "AC-17(3)",
        "SC-7",
        "SC-7(3)"
      ]
    },
    {
      "AWSConfigIdentifier": "CODEBUILD_PROJECT_ENVVAR_AWSCRED_CHECK",
      "CfnGuardFile": "rules/aws/codebuild/codebuild_project_envvar_awscred_check.guard",
      "Controls": [
        "AC-6",
        "IA-5(7)",
        "SA-3(a)"
      ]
    },
    {
      "AWSConfigIdentifier": "EC2_IMDSV2_CHECK",
      "CfnGuardFile": "rules/aws/amazon_ec2/ec2_imdsv2_check.guard",
      "Controls": [
        "AC-6"
      ]
    },
    {
      "AWSConfigIdentifier": "IAM_NO_INLINE_POLICY_CHECK",
      "CfnGuardFile": "rules/aws/iam/iam_no_inline_policy_check.guard",
      "Controls": [
        "AC-6"
      ]
    },
    {
      "AWSConfigIdentifier": "ALB_HTTP_TO_HTTPS_REDIRECTION_CHECK",
      "CfnGuardFile": "rules/aws/elastic_load_balancing_v2/alb_http_to_https_redirection_check.guard",
      "Controls": [
        "AC-17(2)",
        "SC-7",
        "SC-8",
        "SC-8(1)",
        "SC-13",
        "SC-23"
      ]
    },
    {
      "AWSConfigIdentifier": "REDSHIFT_REQUIRE_TLS_SSL",
      "CfnGuardFile": "rules/aws/amazon_redshift/redshift_require_tls_ssl.guard",
      "Controls": [
        "AC-17(2)",
        "SC-7",
        "SC-8",
        "SC-8(1)",
        "SC-13"
      ]
    },
    {
      "AWSConfigIdentifier": "S3_BUCKET_SSL_REQUESTS_ONLY",
      "CfnGuardFile": "rules/aws/amazon_s3/s3_bucket_ssl_requests_only.guard",
      "Controls": [
        "AC-17(2)",
        "SC-7",
        "SC-8",
        "SC-8(1)",
        "SC-13"
      ]
    },
    {
      "AWSConfigIdentifier": "ELB_ACM_CERTIFICATE_REQUIRED",
      "CfnGuardFile": "rules/aws/elastic_load_balancing/elb_acm_certificate_required.guard",
      "Controls": [
        "AC-17(2)",
        "SC-7",
        "SC-8",
        "SC-8(1)",
        "SC-13"
      ]
    },
    {
      "AWSConfigIdentifier": "ALB_HTTP_DROP_INVALID_HEADER_ENABLED",
      "CfnGuardFile": "rules/aws/elastic_load_balancing_v2/alb_http_drop_invalid_header_enabled.guard",
      "Controls": [
        "AC-17(2)",
        "SC-7",
        "SC-8",
        "SC-8(1)",
        "SC-23"
      ]
    },
    {
      "AWSConfigIdentifier": "ELB_TLS_HTTPS_LISTENERS_ONLY",
      "CfnGuardFile": "rules/aws/elastic_load_balancing/elb_tls_https_listeners_only.guard",
      "Controls": [
        "AC-17(2)",
        "SC-7",
        "SC-8",
        "SC-8(1)",
        "SC-23"
      ]
    },
    {
      "AWSConfigIdentifier": "API_GW_EXECUTION_LOGGING_ENABLED",
      "CfnGuardFile": "rules/aws/api_gateway_v2/api_gw_execution_logging_enabled.guard",
      "Controls": [
        "AU-2(a)(d)",
        "AU-3",
        "AU-12(a)(c)"
      ]
    },
    {
      "AWSConfigIdentifier": "ELB_LOGGING_ENABLED",
      "CfnGuardFile": "rules/aws/elastic_load_balancing/elb_logging_enabled.guard",
      "Controls": [
        "AU-2(a)(d)",
        "AU-3",
        "AU-12(a)(c)"
      ]
    },
    {
      "AWSConfigIdentifier": "VPC_FLOW_LOGS_ENABLED",
      "CfnGuardFile": "rules/aws/amazon_ec2/vpc_flow_logs_enabled.guard",
      "Controls": [
        "AU-2(a)(d)",
        "AU-3",
        "AU-12(a)(c)"
      ]
    },
    {
      "AWSConfigIdentifier": "WAFV2_LOGGING_ENABLED",
      "CfnGuardFile": "rules/aws/aws_waf_v2/wafv2_logging_enabled.guard",
      "Controls": [
        "AU-2(a)(d)",
        "AU-3",
        "AU-12(a)(c)",
        "SC-7",
        "SI-4(a)(b)(c)"
      ]
    },
    {
      "AWSConfigIdentifier": "CLOUD_TRAIL_ENCRYPTION_ENABLED",
      "CfnGuardFile": "rules/aws/cloudtrail/cloud_trail_encryption_enabled.guard",
      "Controls": [
        "AU-9",
        "SC-13",
        "SC-28"
      ]
    },
    {
      "AWSConfigIdentifier": "CLOUDWATCH_LOG_GROUP_ENCRYPTED",
      "CfnGuardFile": "rules/aws/cloudwatch/cloudwatch_log_group_encrypted.guard",
      "Controls": [
        "AU-9",
        "SC-13",
        "SC-28"
      ]
    },
    {
      "AWSConfigIdentifier": "S3_BUCKET_REPLICATION_ENABLED",
      "CfnGuardFile": "rules/aws/amazon_s3/s3_bucket_replication_enabled.guard",
      "Controls": [
        "AU-9(2)",
        "CP-9(b)",
        "CP-10",
        "SC-5",
        "SC-36"
      ]
    },
    {
      "AWSConfigIdentifier": "CW_LOGGROUP_RETENTION_PERIOD_CHECK",
      "CfnGuardFile": "rules/aws/cloudwatch/cw_loggroup_retention_period_check.guard",
      "Controls": [
        "AU-11",
        "SI-12"
      ]
    },
    {
      "AWSConfigIdentifier": "EC2_INSTANCE_DETAILED_MONITORING_ENABLED",
      "CfnGuardFile": "rules/aws/amazon_ec2/ec2_instance_detailed_monitoring_enabled.guard",
      "Controls": [
        "CA-7(a)(b)",
        "SI-4(2)",
        "SI-4(a)(b)(c)"
      ]
    },
    {
      "AWSConfigIdentifier": "RDS_ENHANCED_MONITORING_ENABLED",
      "CfnGuardFile": "rules/aws/amazon_rds/rds_enhanced_monitoring_enabled.guard",
      "Controls": [
        "CA-7(a)(b)"
      ]
    },
    {
      "AWSConfigIdentifier": "EC2_INSTANCE_MANAGED_BY_SYSTEMS_MANAGER",
      "CfnGuardFile": "rules/aws/amazon_ec2/ec2_instance_managed_by_systems_manager.guard",
      "Controls": [
        "CM-2",
        "CM-7(a)",
        "CM-8(1)",
        "CM-8(3)(a)",
        "SA-3(a)",
        "SA-10",
        "SI-2(2)",
        "SI-7(1)"
      ]
    },
    {
      "AWSConfigIdentifier": "EC2_MANAGEDINSTANCE_ASSOCIATION_COMPLIANCE_STATUS_CHECK",
      "CfnGuardFile": "rules/aws/amazon_ec2/ec2_managedinstance_association_compliance_status_check.guard",
      "Controls": [
        "CM-2",
        "CM-7(a)",
        "CM-8(3)(a)",
        "SI-2(2)"
      ]
    },
    {
      "AWSConfigIdentifier": "EC2_STOPPED_INSTANCE",
      "CfnGuardFile": "rules/aws/amazon_ec2/ec2_stopped_instance.guard",
      "Controls": [
        "CM-2"
      ]
    },
    {
      "AWSConfigIdentifier": "EC2_VOLUME_INUSE_CHECK",
      "CfnGuardFile": "rules/aws/amazon_ec2/ec2_volume_inuse_check.guard",
      "Controls": [
        "CM-2",
        "SC-4"
      ]
    },
    {
      "AWSConfigIdentifier": "ELB_DELETION_PROTECTION_ENABLED",
      "CfnGuardFile": "rules/aws/elastic_load_balancing/elb_deletion_protection_enabled.guard",
      "Controls": [
        "CM-2",
        "CP-10"
      ]
    },
    {
      "AWSConfigIdentifier": "CLOUDTRAIL_SECURITY_TRAIL_ENABLED",
      "CfnGuardFile": "rules/aws/cloudtrail/cloudtrail_security_trail_enabled.guard",
      "Controls": [
        "CM-2"
      ]
    },
    {
      "AWSConfigIdentifier": "EC2_MANAGEDINSTANCE_PATCH_COMPLIANCE_STATUS_CHECK",
      "CfnGuardFile": "rules/aws/amazon_ec2/ec2_managedinstance_patch_compliance_status_check.guard",
      "Controls": [
        "CM-8(3)(a)",
        "SI-2(2)",
        "SI-7(1)"
      ]
    },
    {
      "AWSConfigIdentifier": "DB_INSTANCE_BACKUP_ENABLED",
      "CfnGuardFile": "rules/aws/amazon_rds/db_instance_backup_enabled.guard",
      "Controls": [
        "CP-9(b)",
        "CP-10",
        "SI-12"
      ]
    },
    {
      "AWSConfigIdentifier": "DYNAMODB_PITR_ENABLED",
      "CfnGuardFile": "rules/aws/dynamodb/dynamodb_pitr_enabled.guard",
      "Controls": [
        "CP-9(b)",
        "CP-10",
        "SI-12"
      ]
    },
    {
      "AWSConfigIdentifier": "ELASTICACHE_REDIS_CLUSTER_AUTOMATIC_BACKUP_CHECK",
      "CfnGuardFile": "rules/aws/elasticache/elasticache_redis_cluster_automatic_backup_check.guard",
      "Controls": [
        "CP-9(b)",
        "CP-10",
        "SI-12"
      ]
    },
    {
      "AWSConfigIdentifier": "DYNAMODB_IN_BACKUP_PLAN",
      "CfnGuardFile": "rules/aws/dynamodb/dynamodb_in_backup_plan.guard",
      "Controls": [
        "CP-9(b)",
        "CP-10",
        "SI-12"
      ]
    },
    {
      "AWSConfigIdentifier": "EBS_IN_BACKUP_PLAN",
      "CfnGuardFile": "rules/aws/amazon_ec2/ebs_in_backup_plan.guard",
      "Controls": [
        "CP-9(b)",
        "CP-10",
        "SI-12"
      ]
    },
    {
      "AWSConfigIdentifier": "EFS_IN_BACKUP_PLAN",
      "CfnGuardFile": "rules/aws/amazon_efs/efs_in_backup_plan.guard",
      "Controls": [
        "CP-9(b)",
        "CP-10",
        "SI-12"
      ]
    },
    {
      "AWSConfigIdentifier": "RDS_IN_BACKUP_PLAN",
      "CfnGuardFile": "rules/aws/amazon_rds/rds_in_backup_plan.guard",
      "Controls": [
        "CP-9(b)",
        "CP-10",
        "SI-12"
      ]
    },
    {
      "AWSConfigIdentifier": "DYNAMODB_AUTOSCALING_ENABLED",
      "CfnGuardFile": "rules/aws/dynamodb/dynamodb_autoscaling_enabled.guard",
      "Controls": [
        "CP-10",
        "SC-5"
      ]
    },
    {
      "AWSConfigIdentifier": "RDS_MULTI_AZ_SUPPORT",
      "CfnGuardFile": "rules/aws/amazon_rds/rds_multi_az_support.guard",
      "Controls": [
        "CP-10",
        "SC-5",
        "SC-36"
      ]
    },
    {
      "AWSConfigIdentifier": "S3_BUCKET_VERSIONING_ENABLED",
      "CfnGuardFile": "rules/aws/amazon_s3/s3_bucket_versioning_enabled.guard",
      "Controls": [
        "CP-10",
        "SI-12"
      ]
    },
    {
      "AWSConfigIdentifier": "VPC_VPN_2_TUNNELS_UP",
      "CfnGuardFile": "rules/aws/amazon_ec2/vpc_vpn_2_tunnels_up.guard",
      "Controls": [
        "CP-10"
      ]
    },
    {
      "AWSConfigIdentifier": "ELB_CROSS_ZONE_LOAD_BALANCING_ENABLED",
      "CfnGuardFile": "rules/aws/elastic_load_balancing/elb_cross_zone_load_balancing_enabled.guard",
      "Controls": [
        "CP-10",
        "SC-5"
      ]
    },
    {
      "AWSConfigIdentifier": "ROOT_ACCOUNT_HARDWARE_MFA_ENABLED",
      "CfnGuardFile": "rules/aws/iam/root_account_hardware_mfa_enabled.guard",
      "Controls": [
        "IA-2(1)(11)"
      ]
    },
    {
      "AWSConfigIdentifier": "MFA_ENABLED_FOR_IAM_CONSOLE_ACCESS",
      "CfnGuardFile": "rules/aws/iam/mfa_enabled_for_iam_console_access.guard",
      "Controls": [
        "IA-2(1)(2)(11)"
      ]
    },
    {
      "AWSConfigIdentifier": "IAM_USER_MFA_ENABLED",
      "CfnGuardFile": "rules/aws/iam/iam_user_mfa_enabled.guard",
      "Controls": [
        "IA-2(1)(2)(11)"
      ]
    },
    {
      "AWSConfigIdentifier": "GUARDDUTY_NON_ARCHIVED_FINDINGS",
      "CfnGuardFile": "rules/aws/guardduty/guardduty_non_archived_findings.guard",
      "Controls": [
        "IR-4(1)",
        "IR-6(1)",
        "IR-7(1)",
        "RA-5",
        "SA-10",
        "SI-4(a)(b)(c)"
      ]
    },
    {
      "AWSConfigIdentifier": "CODEBUILD_PROJECT_SOURCE_REPO_URL_CHECK",
      "CfnGuardFile": "rules/aws/codebuild/codebuild_project_source_repo_url_check.guard",
      "Controls": [
        "SA-3(a)"
      ]
    },
    {
      "AWSConfigIdentifier": "AUTOSCALING_GROUP_ELB_HEALTHCHECK_REQUIRED",
      "CfnGuardFile": "rules/aws/amazon_ec2_auto_scaling/autoscaling_group_elb_healthcheck_required.guard",
      "Controls": [
        "SC-5"
      ]
    },
    {
      "AWSConfigIdentifier": "RDS_INSTANCE_DELETION_PROTECTION_ENABLED",
      "CfnGuardFile": "rules/aws/amazon_rds/rds_instance_deletion_protection_enabled.guard",
      "Controls": [
        "SC-5"
      ]
    },
    {
      "AWSConfigIdentifier": "ALB_WAF_ENABLED",
      "CfnGuardFile": "rules/aws/elastic_load_balancing_v2/alb_waf_enabled.guard",
      "Controls": [
        "SC-7",
        "SI-4(a)(b)(c)"
      ]
    },
    {
      "AWSConfigIdentifier": "ELASTICSEARCH_NODE_TO_NODE_ENCRYPTION_CHECK",
      "CfnGuardFile": "rules/aws/opensearch_service/elasticsearch_node_to_node_encryption_check.guard",
      "Controls": [
        "SC-7",
        "SC-8",
        "SC-8(1)"
      ]
    },
    {
      "AWSConfigIdentifier": "CMK_BACKING_KEY_ROTATION_ENABLED",
      "CfnGuardFile": "rules/aws/aws_kms/cmk_backing_key_rotation_enabled.guard",
      "Controls": [
        "SC-12"
      ]
    },
    {
      "AWSConfigIdentifier": "KMS_CMK_NOT_SCHEDULED_FOR_DELETION",
      "CfnGuardFile": "rules/aws/aws_kms/kms_cmk_not_scheduled_for_deletion.guard",
      "Controls": [
        "SC-12",
        "SC-28"
      ]
    },
    {
      "AWSConfigIdentifier": "API_GW_CACHE_ENABLED_AND_ENCRYPTED",
      "CfnGuardFile": "rules/aws/api_gateway_v2/api_gw_cache_enabled_and_encrypted.guard",
      "Controls": [
        "SC-13",
        "SC-28"
      ]
    },
    {
      "AWSConfigIdentifier": "EFS_ENCRYPTED_CHECK",
      "CfnGuardFile": "rules/aws/amazon_efs/efs_encrypted_check.guard",
      "Controls": [
        "SC-13",
        "SC-28"
      ]
    },
    {
      "AWSConfigIdentifier": "ELASTICSEARCH_ENCRYPTED_AT_REST",
      "CfnGuardFile": "rules/aws/opensearch_service/elasticsearch_encrypted_at_rest.guard",
      "Controls": [
        "SC-13",
        "SC-28"
      ]
    },
    {
      "AWSConfigIdentifier": "ENCRYPTED_VOLUMES",
      "CfnGuardFile": "rules/aws/amazon_ec2/encrypted_volumes.guard",
      "Controls": [
        "SC-13",
        "SC-28"
      ]
    },
    {
      "AWSConfigIdentifier": "RDS_STORAGE_ENCRYPTED",
      "CfnGuardFile": "rules/aws/amazon_rds/rds_storage_encrypted.guard",
      "Controls": [
        "SC-13",
        "SC-28"
      ]
    },
    {
      "AWSConfigIdentifier": "S3_BUCKET_SERVER_SIDE_ENCRYPTION_ENABLED",
      "CfnGuardFile": "rules/aws/amazon_s3/s3_bucket_server_side_encryption_enabled.guard",
      "Controls": [
        "SC-13",
        "SC-28"
      ]
    },
    {
      "AWSConfigIdentifier": "SAGEMAKER_ENDPOINT_CONFIGURATION_KMS_KEY_CONFIGURED",
      "CfnGuardFile": "rules/aws/amazon_sagemaker/sagemaker_endpoint_configuration_kms_key_configured.guard",
      "Controls": [
        "SC-13",
        "SC-28"
      ]
    },
    {
      "AWSConfigIdentifier": "SAGEMAKER_NOTEBOOK_INSTANCE_KMS_KEY_CONFIGURED",
      "CfnGuardFile": "rules/aws/amazon_sagemaker/sagemaker_notebook_instance_kms_key_configured.guard",
      "Controls": [
        "SC-13",
        "SC-28"
      ]
    },
    {
      "AWSConfigIdentifier": "SNS_ENCRYPTED_KMS",
      "CfnGuardFile": "rules/aws/amazon_sns/sns_encrypted_kms.guard",
      "Controls": [
        "SC-13",
        "SC-28"
      ]
    },
    {
      "AWSConfigIdentifier": "DYNAMODB_TABLE_ENCRYPTED_KMS",
      "CfnGuardFile": "rules/aws/dynamodb/dynamodb_table_encrypted_kms.guard",
      "Controls": [
        "SC-13"
      ]
    },
    {
      "AWSConfigIdentifier": "S3_BUCKET_DEFAULT_LOCK_ENABLED",
      "CfnGuardFile": "rules/aws/amazon_s3/s3_bucket_default_lock_enabled.guard",
      "Controls": [
        "SC-28"
      ]
    },
    {
      "AWSConfigIdentifier": "EC2_EBS_ENCRYPTION_BY_DEFAULT",
      "CfnGuardFile": "rules/aws/amazon_ec2/ec2_ebs_encryption_by_default.guard",
      "Controls": [
        "SC-28"
      ]
    },
    {
      "AWSConfigIdentifier": "RDS_SNAPSHOT_ENCRYPTED",
      "CfnGuardFile": "rules/aws/amazon_rds/rds_snapshot_encrypted.guard",
      "Controls": [
        "SC-28"
      ]
    },
    {
      "AWSConfigIdentifier": "CLOUD_TRAIL_LOG_FILE_VALIDATION_ENABLED",
      "CfnGuardFile": "rules/aws/cloudtrail/cloud_trail_log_file_validation_enabled.guard",
      "Controls": [
        "SI-7",
        "SI-7(1)"
      ]
    }
  ]
}